image_converter/__init__.py
image_converter/image_converter.py
image_converters-0.1.1.dist-info/LICENSE
image_converters-0.1.1.dist-info/METADATA
image_converters-0.1.1.dist-info/WHEEL
image_converters-0.1.1.dist-info/top_level.txt
image_converters-0.1.1.dist-info/RECORD
