Metadata-Version: 2.1
Name: image-converters
Version: 0.1.1
Summary: ImageConverter is a Python Package that provides methods to convert images between different formats, such as bytes and base64 encoding. It uses the OpenCV library for image processing.
Home-page: https://github.com/tanveersultan53/image_converters
Author: Tanveer Sultan
Author-email: engr.tanveersultan53@gmail.com
Classifier: Development Status :: 5 - Production/Stable
Classifier: Intended Audience :: Developers
Classifier: License :: OSI Approved :: MIT License
Classifier: Programming Language :: Python :: 3
Classifier: Programming Language :: Python :: 3.6
Classifier: Programming Language :: Python :: 3.7
Classifier: Programming Language :: Python :: 3.8
Classifier: Programming Language :: Python :: 3.9
Classifier: Programming Language :: Python :: 3.10
Classifier: Programming Language :: Python :: 3.11
Classifier: Programming Language :: Python :: 3.12
License-File: LICENSE
Requires-Dist: opencv-python
Requires-Dist: numpy
